niftypad/__init__.py
niftypad/__main__.py
niftypad/_dist_ver.py
niftypad/basis.py
niftypad/kp.py
niftypad/kt.py
niftypad/models.py
niftypad/tac.py
niftypad/weight.py
niftypad/api/__init__.py
niftypad/api/readers.py
niftypad/image_process/__init__.py
niftypad/image_process/motion_correction.py
niftypad/image_process/parametric_image.py
niftypad/image_process/regions.py
niftypad/image_process/transforms.py
niftypad-2.0.0.dist-info/LICENSE
niftypad-2.0.0.dist-info/METADATA
niftypad-2.0.0.dist-info/WHEEL
niftypad-2.0.0.dist-info/entry_points.txt
niftypad-2.0.0.dist-info/top_level.txt
niftypad-2.0.0.dist-info/RECORD
