Metadata-Version: 2.1
Name: niftypad
Version: 2.0.0
Summary: Neuroimaging for the Prevention of Alzheimer's Disease
Author-email: Jieqing Jiao <jieqing.jiao@gmail.com>
Maintainer-email: Casper da Costa-Luis <imaging@cdcl.ml>
License: Apache-2.0
Project-URL: documentation, https://github.com/AMYPAD/NiftyPAD/#NiftyPAD
Project-URL: repository, https://github.com/AMYPAD/NiftyPAD
Project-URL: changelog, https://github.com/AMYPAD/NiftyPAD/releases
Keywords: PET,Pharmacokinetic analysis,Reference input-based modelling
Classifier: Development Status :: 4 - Beta
Classifier: Intended Audience :: Developers
Classifier: Intended Audience :: Education
Classifier: Intended Audience :: Healthcare Industry
Classifier: Intended Audience :: Science/Research
Classifier: License :: OSI Approved :: Apache Software License
Classifier: Operating System :: Microsoft :: Windows
Classifier: Operating System :: POSIX :: Linux
Classifier: Programming Language :: Python :: 3
Classifier: Programming Language :: Python :: 3.7
Classifier: Programming Language :: Python :: 3.8
Classifier: Programming Language :: Python :: 3.9
Classifier: Programming Language :: Python :: 3.10
Classifier: Programming Language :: Python :: 3.11
Classifier: Programming Language :: Python :: 3 :: Only
Classifier: Topic :: Scientific/Engineering :: Medical Science Apps.
Requires-Python: >=3.7
License-File: LICENSE
Requires-Dist: matplotlib
Requires-Dist: nibabel
Requires-Dist: numpy
Requires-Dist: scikit-learn
Requires-Dist: tqdm
Requires-Dist: importlib-resources ; python_version < "3.9"
Provides-Extra: dev
Requires-Dist: pytest (>=6) ; extra == 'dev'
Requires-Dist: pytest-cov ; extra == 'dev'
Requires-Dist: pytest-timeout ; extra == 'dev'
